Metadata-Version: 2.1
Name: nonebot2-manage
Version: 0.0.1
Summary: string to date
Home-page: UNKNOWN
Author: YGXB
Author-email: 839682307@qq.com
License: MIT
Platform: UNKNOWN
License-File: LICENSE
